python_rootpath-0.1.9.data/data/rootpath/tests/__fixtures__/rootpath/tests/__fixtures__/projects/py-foo/requirements.txt
python_rootpath-0.1.9.data/data/rootpath/tests/__fixtures__/rootpath/tests/__fixtures__/projects/py-foo/foo/__init__.py
python_rootpath-0.1.9.data/data/rootpath/tests/__fixtures__/rootpath/tests/__fixtures__/projects/py-foo/foo/foo.py
python_rootpath-0.1.9.data/data/rootpath/tests/__fixtures__/rootpath/tests/__fixtures__/projects/py-foo/foo/utils/__init__.py
python_rootpath-0.1.9.data/data/rootpath/tests/__fixtures__/rootpath/tests/__fixtures__/projects/py-foo/vendor/py-bar/requirements.txt
python_rootpath-0.1.9.data/data/rootpath/tests/__fixtures__/rootpath/tests/__fixtures__/projects/py-foo/vendor/py-bar/src/__init__.py
python_rootpath-0.1.9.data/data/rootpath/tests/__fixtures__/rootpath/tests/__fixtures__/projects/py-foo/vendor/py-bar/src/bar.py
python_rootpath-0.1.9.data/data/rootpath/tests/__fixtures__/rootpath/tests/__fixtures__/projects/py-foo/vendor/py-bar/src/utils/__init__.py
python_rootpath-0.1.9.data/data/rootpath/tests/__fixtures__/rootpath/tests/__fixtures__/projects/py-foo/vendor/py-bar/src/utils/package.json
rootpath/__init__.py
rootpath/append.py
rootpath/detect.py
rootpath/tests/__init__.py
rootpath/tests/__main__.py
rootpath/tests/helper.py
rootpath/tests/test_append.py
rootpath/tests/test_detect.py
rootpath/tests/__fixtures__/projects/py-foo/requirements.txt
rootpath/tests/__fixtures__/projects/py-foo/foo/__init__.py
rootpath/tests/__fixtures__/projects/py-foo/foo/foo.py
rootpath/tests/__fixtures__/projects/py-foo/foo/utils/__init__.py
rootpath/tests/__fixtures__/projects/py-foo/vendor/py-bar/requirements.txt
rootpath/tests/__fixtures__/projects/py-foo/vendor/py-bar/src/__init__.py
rootpath/tests/__fixtures__/projects/py-foo/vendor/py-bar/src/bar.py
rootpath/tests/__fixtures__/projects/py-foo/vendor/py-bar/src/utils/__init__.py
rootpath/tests/__fixtures__/projects/py-foo/vendor/py-bar/src/utils/package.json
python_rootpath-0.1.9.dist-info/METADATA
python_rootpath-0.1.9.dist-info/WHEEL
python_rootpath-0.1.9.dist-info/top_level.txt
python_rootpath-0.1.9.dist-info/zip-safe
python_rootpath-0.1.9.dist-info/RECORD
