Metadata-Version: 2.4
Name: python-rootpath
Version: 0.1.9
Summary: Python project/package root path detection.
Home-page: https://github.com/grimen/python-rootpath
Download-URL: https://github.com/grimen/python-rootpath
Author: Jonas Grimfelt
Author-email: grimen@gmail.com
License: MIT
Project-URL: repository, https://github.com/grimen/python-rootpath
Project-URL: bugs, https://github.com/grimen/python-rootpath/issues
Keywords: python,utlity,common,root,rootpath,root-path,detect,autodetect,auto-detect,project-root,project-root-path,package-root,package-root-path
Classifier: Topic :: Software Development :: Libraries
Classifier: Development Status :: 5 - Production/Stable
Classifier: Intended Audience :: Developers
Classifier: License :: OSI Approved :: MIT License
Classifier: Operating System :: POSIX
Classifier: Programming Language :: Python
Classifier: Programming Language :: Python :: 2
Classifier: Programming Language :: Python :: 3
Classifier: Programming Language :: Python :: Implementation :: CPython
Classifier: Programming Language :: Python :: Implementation :: PyPy
Requires-Dist: six>=1.11.0
Dynamic: author
Dynamic: author-email
Dynamic: classifier
Dynamic: description
Dynamic: description-content-type
Dynamic: download-url
Dynamic: home-page
Dynamic: keywords
Dynamic: license
Dynamic: project-url
Dynamic: requires-dist
Dynamic: summary
